{
  "nodes": [
    { "id": "crisisnews", "label": "CrisisNews", "type": "research", "url": "/research/crisisnews" },
    { "id": "prism", "label": "PRISM", "type": "research", "url": "/research/prism" },
    { "id": "beyond-removal", "label": "Beyond Removal", "type": "research", "url": "/research/beyond-removal" },
    { "id": "multi-agent-sim", "label": "Multi-Agent Sim", "type": "research", "url": "/research/multi-agent-sim" },
    { "id": "chi-2025", "label": "CHI 2025", "type": "activity", "url": "/activities/chi-2025" },
    { "id": "un-ga-hlw", "label": "UN GA HLW", "type": "activity", "url": "/activities/un-ga-hlw" },
    { "id": "student-council", "label": "Student Council", "type": "activity", "url": "/activities/student-council" },
    { "id": "valedictorian", "label": "Valedictorian", "type": "activity", "url": "/activities/valedictorian" },
    { "id": "participatory-budget", "label": "Participatory Budget", "type": "activity", "url": "/activities/participatory-budget" },
    { "id": "misinformation", "label": "Misinformation", "type": "theme" },
    { "id": "platform-governance", "label": "Platform Governance", "type": "theme" },
    { "id": "content-moderation", "label": "Content Moderation", "type": "theme" },
    { "id": "ai-policy", "label": "AI Policy", "type": "theme" },
    { "id": "participatory-governance", "label": "Participatory Governance", "type": "theme" },
    { "id": "kaist", "label": "KAIST", "type": "institution" },
    { "id": "columbia-sipa", "label": "Columbia SIPA", "type": "institution" }
  ],
  "edges": [
    { "source": "crisisnews", "target": "misinformation" },
    { "source": "crisisnews", "target": "platform-governance" },
    { "source": "prism", "target": "misinformation" },
    { "source": "prism", "target": "platform-governance" },
    { "source": "prism", "target": "columbia-sipa" },
    { "source": "beyond-removal", "target": "platform-governance" },
    { "source": "beyond-removal", "target": "content-moderation" },
    { "source": "multi-agent-sim", "target": "misinformation" },
    { "source": "multi-agent-sim", "target": "ai-policy" },
    { "source": "chi-2025", "target": "misinformation" },
    { "source": "chi-2025", "target": "kaist" },
    { "source": "un-ga-hlw", "target": "participatory-governance" },
    { "source": "un-ga-hlw", "target": "columbia-sipa" },
    { "source": "student-council", "target": "participatory-governance" },
    { "source": "student-council", "target": "kaist" },
    { "source": "student-council", "target": "participatory-budget" },
    { "source": "valedictorian", "target": "student-council" },
    { "source": "valedictorian", "target": "kaist" },
    { "source": "participatory-budget", "target": "participatory-governance" },
    { "source": "participatory-budget", "target": "kaist" },
    { "source": "misinformation", "target": "platform-governance" },
    { "source": "platform-governance", "target": "content-moderation" },
    { "source": "content-moderation", "target": "ai-policy" },
    { "source": "ai-policy", "target": "participatory-governance" }
  ]
}
